apolo_all/__init__.py
apolo_all-26.1.0.dist-info/METADATA
apolo_all-26.1.0.dist-info/WHEEL
apolo_all-26.1.0.dist-info/entry_points.txt
apolo_all-26.1.0.dist-info/licenses/LICENSE
apolo_all-26.1.0.dist-info/RECORD
